uot/__init__.py
uot/algorithms/col_gen.py
uot/algorithms/gradient_ascent.py
uot/algorithms/lbfgs.py
uot/algorithms/lp.py
uot/algorithms/pdgd.py
uot/algorithms/sinkhorn.py
uot/algorithms/utils.py
uot/algorithms/rapdhg/__init__.py
uot/algorithms/rapdhg/iteration_stats_utils.py
uot/algorithms/rapdhg/loop_utils.py
uot/algorithms/rapdhg/mp_io.py
uot/algorithms/rapdhg/preprocess.py
uot/algorithms/rapdhg/rapdhg.py
uot/algorithms/rapdhg/restart.py
uot/algorithms/rapdhg/solver_log.py
uot/algorithms/rapdhg/termination.py
uot/algorithms/rapdhg/utils.py
uot/algorithms/rapdhg/strategies/reg_strategy.py
uot/algorithms/rapdhg/strategies/update_strategy.py
uot/analysis/__init__.py
uot/analysis/analysis.py
uot/analysis/plotter.py
uot/analysis/run_tests.py
uot/analysis/split_results.py
uot/data/__init__.py
uot/data/dataset_loader.py
uot/data/measure.py
uot/experiments/__init__.py
uot/experiments/experiment.py
uot/experiments/measurement.py
uot/experiments/runner.py
uot/experiments/real_data/color_transfer/color_transfer.py
uot/experiments/real_data/color_transfer/color_transfer_metrics.py
uot/experiments/real_data/color_transfer/color_transfer_problem.py
uot/experiments/real_data/color_transfer/experiment.py
uot/experiments/real_data/color_transfer/image_data.py
uot/experiments/real_data/color_transfer/measurement.py
uot/experiments/real_data/color_transfer/measurement_helpers.py
uot/experiments/real_data/color_transfer/runner.py
uot/experiments/real_data/color_transfer/utils.py
uot/experiments/real_data/color_transfer/visualization.py
uot/experiments/real_data/mnist_classification/count_pairwise_distances.py
uot/experiments/real_data/mnist_classification/mnist_classification.py
uot/experiments/synthetic/benchmark.py
uot/experiments/synthetic/benchmark_gaussians.py
uot/problems/__init__.py
uot/problems/barycenter_problem.py
uot/problems/base_problem.py
uot/problems/hdf5_store.py
uot/problems/inspect_store.py
uot/problems/iterator.py
uot/problems/multi_marginal.py
uot_bench-0.1.2.dist-info/licenses/LICENSE
uot_bench-0.1.2.dist-info/METADATA
uot_bench-0.1.2.dist-info/WHEEL
uot_bench-0.1.2.dist-info/top_level.txt
uot_bench-0.1.2.dist-info/RECORD
