Metadata-Version: 2.4
Name: uot_bench
Version: 0.1.2
Summary: Utilities for optimal transport algorithms and benchmarking
Author-email: Ivan Zhytkevych <aipyth.func@gmail.com>, Maksym-Vasyl Tarnavskyi <tarnavskyi.pn@ucu.edu.ua>, Maksym Zhuk <zhuk.pn@ucu.edu.ua>
License: MIT
Project-URL: Homepage, https://github.com/AI-Quantum-Research-Group/uot-bench
Project-URL: Repository, https://github.com/AI-Quantum-Research-Group/uot-bench
Project-URL: Issues, https://github.com/AI-Quantum-Research-Group/uot-bench/issues
Classifier: Programming Language :: Python :: 3
Classifier: License :: OSI Approved :: MIT License
Requires-Python: >=3.11
License-File: LICENSE
Requires-Dist: POT
Requires-Dist: PyYAML
Requires-Dist: chex
Requires-Dist: gpu-tracker
Requires-Dist: h5py
Requires-Dist: jax
Requires-Dist: jaxopt
Requires-Dist: numpy
Requires-Dist: optax
Requires-Dist: pandas
Requires-Dist: scikit-learn
Requires-Dist: scipy
Requires-Dist: toolz
Requires-Dist: tqdm
Provides-Extra: cuda12
Requires-Dist: jax[cuda12]; extra == "cuda12"
Provides-Extra: color-transfer
Requires-Dist: dash; extra == "color-transfer"
Requires-Dist: opencv-python; extra == "color-transfer"
Requires-Dist: Pillow; extra == "color-transfer"
Requires-Dist: scikit-image; extra == "color-transfer"
Requires-Dist: plotly; extra == "color-transfer"
Requires-Dist: matplotlib; extra == "color-transfer"
Provides-Extra: gurobi
Requires-Dist: gurobipy; extra == "gurobi"
Provides-Extra: image-analysis
Requires-Dist: Pillow; extra == "image-analysis"
Requires-Dist: scikit-image; extra == "image-analysis"
Requires-Dist: matplotlib; extra == "image-analysis"
Requires-Dist: seaborn; extra == "image-analysis"
Requires-Dist: dataframe-image; extra == "image-analysis"
Requires-Dist: ipython; extra == "image-analysis"
Provides-Extra: viz
Requires-Dist: matplotlib; extra == "viz"
Requires-Dist: plotly; extra == "viz"
Requires-Dist: seaborn; extra == "viz"
Requires-Dist: dataframe-image; extra == "viz"
Requires-Dist: ipython; extra == "viz"
Provides-Extra: testing
Requires-Dist: pytest>=7.0; extra == "testing"
Provides-Extra: lint
Requires-Dist: black>=23.3.0; extra == "lint"
Requires-Dist: ruff>=0.4.1; extra == "lint"
Dynamic: license-file
